Makefile
atlas
setup.py
atlas.egg-info/PKG-INFO
atlas.egg-info/SOURCES.txt
atlas.egg-info/dependency_links.txt
atlas.egg-info/requires.txt
atlas.egg-info/top_level.txt
atlas.egg-info/zip-safe
src/Makefile
src/__init__.py
src/action.py
src/atlas_main.py
src/component.py
src/constants.py
src/extension.py
src/filecache.py
src/filecache_test.py
src/flags.py
src/globals.py
src/graph.py
src/loader.py
src/log.py
src/metrics.py
src/registry.py
src/setup.py
src/util.py
src/util_test.py
src/mod/__init__.py
src/mod/automake.py
src/mod/automake_config.py
src/mod/cpp_binary.py
src/mod/cpp_exe.py
src/mod/cpp_include.py
src/mod/cpp_library.py
src/mod/cpp_source.py
src/mod/cpp_test.py
src/mod/file.py
src/mod/flex_app.py
src/mod/flex_binary.py
src/mod/flex_library.py
src/mod/flex_test.py
src/mod/protocol_buffer.py
src/mod/python_test.py
src/mod/shell_builder.py
src/mod/shell_test.py
src/mod/test.py
test/Makefile
test/atlas_test.py
test/core_test.py
test/cpp_test.py
test/flex_test.py
test/protobuf_test.py
test/shell_test.py
test/test_constants.py