Metadata-Version: 1.0
Name: atlas
Version: 0.27.0
Summary: Atlas Build Tool - simple, extensible build system.
Home-page: http://code.google.com/p/atlas-build-tool
Author: Mike Parent
Author-email: UNKNOWN
License: Apache 2.0
Keywords: build test
Platform: UNKNOWN
